<?xml version="1.0" encoding="utf-8" ?><dwsync><file name="Harmonetal_nature07974.pdf" server="unix.uidaho.edu//shared/lukeh/webpages/~lukeh/" local="3323879540" remote="2210216132634580546" /><file name="Harmonetal_nature07974_supp.pdf" server="unix.uidaho.edu//shared/lukeh/webpages/~lukeh/" local="3321829626" remote="2210216132634580563" /><file name="nature_makingthepaper.pdf" server="unix.uidaho.edu//shared/lukeh/webpages/~lukeh/" local="3323879461" remote="2210216132634580568" /><file name="nature_newsandviews.pdf" server="unix.uidaho.edu//shared/lukeh/webpages/~lukeh/" local="3323879503" remote="2210216132634580574" /><file name="Nosiletal,TREE2009.pdf" server="unix.uidaho.edu//shared/lukeh/webpages/~lukeh/" local="3316450982" remote="2210216132634580625" /><file name="MacroSyllabus.pdf" server="unix.uidaho.edu//shared/lukeh/webpages/~lukeh/" local="3334326206" remote="3186179744791384659" /><file name="alfaro_et_al_2009.pdf" server="unix.uidaho.edu//shared/lukeh/webpages/~lukeh/" local="3364172351" remote="2134061036752008870" /><file name="arnegardetal_2010.pdf" server="unix.uidaho.edu//shared/lukeh/webpages/~lukeh/" local="3364215975" remote="2134061036752008872" /><file name="Baileyetal_2009.pdf" server="unix.uidaho.edu//shared/lukeh/webpages/~lukeh/" local="3365553777" remote="2134061036752008873" /><file name="hageyetal_2010.pdf" server="unix.uidaho.edu//shared/lukeh/webpages/~lukeh/" local="3365552822" remote="2134061036752008873" /><file name="harmon2010JC.pdf" server="unix.uidaho.edu//shared/lukeh/webpages/~lukeh/" local="3363024547" remote="2134061036752008873" /><file name="harmon_cv.pdf" server="unix.uidaho.edu//shared/lukeh/webpages/~lukeh/" local="3409111107" remote="469842539096274772" /><file name="harmonetal_2010_earlyBurst.pdf" server="unix.uidaho.edu//shared/lukeh/webpages/~lukeh/" local="3365423681" remote="2134061036752008873" /><file name="HarmonGlor_2010_Evolution.pdf" server="unix.uidaho.edu//shared/lukeh/webpages/~lukeh/" local="3364080303" remote="2134061036752008873" /><file name="ingrametal_2009.pdf" server="unix.uidaho.edu//shared/lukeh/webpages/~lukeh/" local="3364496217" remote="2134061036752008874" /><file name="matthewsetal_2010.pdf" server="unix.uidaho.edu//shared/lukeh/webpages/~lukeh/" local="3359508625" remote="2134061036752008875" /><file name="santinietal_2009.pdf" server="unix.uidaho.edu//shared/lukeh/webpages/~lukeh/" local="3365552482" remote="2134061036752008875" /><file name="yoderetal_2010.pdf" server="unix.uidaho.edu//shared/lukeh/webpages/~lukeh/" local="3365423797" remote="2134061036752008875" /><file name="harmonCvJan12.pdf" server="unix.uidaho.edu//shared/lukeh/webpages/~lukeh/" local="3409935356" remote="425545500538035793" /><file name="brocketal_2011.pdf" server="unix.uidaho.edu//shared/lukeh/webpages/~lukeh/" local="3417012739" remote="517834108532653034" /><file name="carlsonetal_2011.pdf" server="unix.uidaho.edu//shared/lukeh/webpages/~lukeh/" local="3417013048" remote="517834108532653035" /><file name="eastmanetal_2011_auteur.pdf" server="unix.uidaho.edu//shared/lukeh/webpages/~lukeh/" local="3417012883" remote="517834108532653035" /><file name="eastmanetal_2011_biofilms.pdf" server="unix.uidaho.edu//shared/lukeh/webpages/~lukeh/" local="3417012835" remote="517834108532653038" /><file name="godsoeHarmon_2012.pdf" server="unix.uidaho.edu//shared/lukeh/webpages/~lukeh/" local="3417012288" remote="517834108532653039" /><file name="harmonCvApr12.pdf" server="unix.uidaho.edu//shared/lukeh/webpages/~lukeh/" local="3417011670" remote="517834108532653039" /><file name="Revell_and_Harmon_2008.pdf" server="unix.uidaho.edu//shared/lukeh/webpages/~lukeh/" local="3417013109" remote="517834108532653040" /><file name="rosenblumandharmon_2011.pdf" server="unix.uidaho.edu//shared/lukeh/webpages/~lukeh/" local="3417012986" remote="517834108532653040" /><file name="rosindelletal_2012.pdf" server="unix.uidaho.edu//shared/lukeh/webpages/~lukeh/" local="3417012390" remote="517834108532653040" /><file name="slateretal_2012_ABC.pdf" server="unix.uidaho.edu//shared/lukeh/webpages/~lukeh/" local="3417012572" remote="517834108532653041" /><file name="smithetal_2011.pdf" server="unix.uidaho.edu//shared/lukeh/webpages/~lukeh/" local="3417012778" remote="517834108532653041" /><file name="ingrametal_2012.pdf" server="unix.uidaho.edu//shared/lukeh/webpages/~lukeh/" local="3452617238" remote="572948125342947306" /><file name="pennelletal_12.pdf" server="unix.uidaho.edu//shared/lukeh/webpages/~lukeh/" local="3417039263" remote="572948125342947308" /><file name="rosindellHarmon_2013.pdf" server="unix.uidaho.edu//shared/lukeh/webpages/~lukeh/" local="3452622604" remote="572948125342947308" /><file name="slateretal_2012_fossils.pdf" server="unix.uidaho.edu//shared/lukeh/webpages/~lukeh/" local="3452617438" remote="572948125342947309" /><file name="wagneretal_2012.pdf" server="unix.uidaho.edu//shared/lukeh/webpages/~lukeh/" local="3452617112" remote="572948125342947310" /></dwsync>